LICENSE
compose_viz/__init__.py
compose_viz/__main__.py
compose_viz/cli.py
compose_viz/graph.py
compose_viz/models/__init__.py
compose_viz/models/compose.py
compose_viz/models/device.py
compose_viz/models/extends.py
compose_viz/models/port.py
compose_viz/models/service.py
compose_viz/models/viz_formats.py
compose_viz/models/volume.py
compose_viz/parser.py
compose_viz/spec/__init__.py
compose_viz/spec/compose_spec.py
compose_viz-0.3.4.dist-info/LICENSE
compose_viz-0.3.4.dist-info/METADATA
compose_viz-0.3.4.dist-info/WHEEL
compose_viz-0.3.4.dist-info/entry_points.txt
compose_viz-0.3.4.dist-info/RECORD
