Metadata-Version: 2.1
Name: compose-viz
Version: 0.3.4
Summary: A compose file visualization tool that supports compose-spec and allows you to gernerate graph in several formats.
Home-page: https://github.com/compose-viz/compose-viz
License: MIT
Author: Xyphuz Wu
Author-email: xyphuzwu@gmail.com
Requires-Python: >=3.9,<4.0
Classifier: License :: OSI Approved :: MIT License
Classifier: Programming Language :: Python :: 3
Classifier: Programming Language :: Python :: 3.9
Classifier: Programming Language :: Python :: 3.10
Classifier: Programming Language :: Python :: 3.11
Classifier: Programming Language :: Python :: 3.12
Requires-Dist: graphviz (>=0.20,<0.21)
Requires-Dist: pydantic-yaml (>=1.3.0,<2.0.0)
Requires-Dist: typer (>=0.4.1,<0.5.0)
Project-URL: Repository, https://github.com/compose-viz/compose-viz
